LICENSE
README.md
requirements.txt
test.py
NonameOrm/__init__.pxd
NonameOrm/__init__.py
NonameOrm/DB/Connector.c
NonameOrm/DB/Connector.cp313-win_amd64.pyd
NonameOrm/DB/Connector.pxd
NonameOrm/DB/Connector.pyi
NonameOrm/DB/Connector.pyx
NonameOrm/DB/DB.c
NonameOrm/DB/DB.cp313-win_amd64.pyd
NonameOrm/DB/DB.pxd
NonameOrm/DB/DB.pyi
NonameOrm/DB/DB.pyx
NonameOrm/DB/Generator.c
NonameOrm/DB/Generator.cp313-win_amd64.pyd
NonameOrm/DB/Generator.pxd
NonameOrm/DB/Generator.pyi
NonameOrm/DB/Generator.pyx
NonameOrm/DB/__init__.pxd
NonameOrm/DB/__init__.py
NonameOrm/DB/utils.py
NonameOrm/Error/BaseOrmError.py
NonameOrm/Error/DBError.py
NonameOrm/Error/PropertyError.py
NonameOrm/Error/QueryError.py
NonameOrm/Error/SqlError.py
NonameOrm/Error/__init__.py
NonameOrm/Ext/DataGenerator.c
NonameOrm/Ext/DataGenerator.cp313-win_amd64.pyd
NonameOrm/Ext/DataGenerator.pyi
NonameOrm/Ext/DataGenerator.pyx
NonameOrm/Ext/Decorators.py
NonameOrm/Ext/Dict.c
NonameOrm/Ext/Dict.cp313-win_amd64.pyd
NonameOrm/Ext/Dict.pxd
NonameOrm/Ext/Dict.pyx
NonameOrm/Ext/PageAble.c
NonameOrm/Ext/PageAble.cp313-win_amd64.pyd
NonameOrm/Ext/PageAble.pxd
NonameOrm/Ext/PageAble.pyi
NonameOrm/Ext/PageAble.pyx
NonameOrm/Ext/__init__.pxd
NonameOrm/Ext/__init__.py
NonameOrm/Model/DataModel.c
NonameOrm/Model/DataModel.cp313-win_amd64.pyd
NonameOrm/Model/DataModel.pxd
NonameOrm/Model/DataModel.pyi
NonameOrm/Model/DataModel.pyx
NonameOrm/Model/ModelExcutor.c
NonameOrm/Model/ModelExcutor.cp313-win_amd64.pyd
NonameOrm/Model/ModelExcutor.pxd
NonameOrm/Model/ModelExcutor.pyi
NonameOrm/Model/ModelExcutor.pyx
NonameOrm/Model/ModelProperty.c
NonameOrm/Model/ModelProperty.cp313-win_amd64.pyd
NonameOrm/Model/ModelProperty.pxd
NonameOrm/Model/ModelProperty.pyi
NonameOrm/Model/ModelProperty.pyx
NonameOrm/Model/__init__.pxd
NonameOrm/Model/__init__.py
NonameOrm/Model/__init__.pyi
NonameOrm.egg-info/PKG-INFO
NonameOrm.egg-info/SOURCES.txt
NonameOrm.egg-info/dependency_links.txt
NonameOrm.egg-info/not-zip-safe
NonameOrm.egg-info/requires.txt
NonameOrm.egg-info/top_level.txt
build/lib.win-amd64-cpython-313/NonameOrm/DB/Connector.c
build/lib.win-amd64-cpython-313/NonameOrm/DB/DB.c
nonameorm-1.2.4.dist-info/licenses/LICENSE
nonameorm-1.2.4.dist-info/METADATA
nonameorm-1.2.4.dist-info/WHEEL
nonameorm-1.2.4.dist-info/top_level.txt
nonameorm-1.2.4.dist-info/RECORD
