Metadata-Version: 2.4
Name: NonameOrm
Version: 1.2.4
Summary: A Orm support asyncio and sync
Home-page: https://gitee.com/otonashi-4/python_async_orm
Author: OToNaShi-4
Author-email: 517431682@qq.com
Keywords: asyncio,aiomysql,orm
Classifier: Intended Audience :: Developers
Classifier: License :: OSI Approved :: MIT License
Classifier: Natural Language :: English
Classifier: Programming Language :: Python :: 3.6
Classifier: Programming Language :: Python :: 3.7
Classifier: Programming Language :: Python :: 3.8
Classifier: Programming Language :: Python :: 3.10
Requires-Python: >=3.7.0
License-File: LICENSE
Requires-Dist: Faker
Requires-Dist: astor
Requires-Dist: case-convert
Requires-Dist: aiosqlite
Requires-Dist: pydantic
Dynamic: author
Dynamic: author-email
Dynamic: classifier
Dynamic: description-content-type
Dynamic: home-page
Dynamic: keywords
Dynamic: license-file
Dynamic: requires-dist
Dynamic: requires-python
Dynamic: summary
